pyYouTubeAnalysis/__init__.py
pyYouTubeAnalysis/cleaner.py
pyYouTubeAnalysis/crawler.py
pyYouTubeAnalysis/extract_locations.py
pyYouTubeAnalysis/phrases.py
pyYouTubeAnalysis/report.py
pyYouTubeAnalysis/run_crawl.py
pyYouTubeAnalysis-1.1.dist-info/LICENSE
pyYouTubeAnalysis-1.1.dist-info/METADATA
pyYouTubeAnalysis-1.1.dist-info/WHEEL
pyYouTubeAnalysis-1.1.dist-info/top_level.txt
pyYouTubeAnalysis-1.1.dist-info/RECORD
