Metadata-Version: 2.1
Name: pyYouTubeAnalysis
Version: 1.1
Summary: Interacting with YouTube Data API and running analysis using NLP
Home-page: https://github.com/jsingh811/pyYouTubeAnalysis
Author: Jyotika Singh
License: UNKNOWN
Platform: UNKNOWN
Classifier: Programming Language :: Python :: 3
Classifier: License :: OSI Approved :: GNU General Public License v3 (GPLv3)
Classifier: Operating System :: OS Independent
Requires-Python: >=3.6, <4
License-File: LICENSE
Requires-Dist: google-api-python-client (==1.7.5)
Requires-Dist: pytest (==3.9.2)
Requires-Dist: spacy (==3.0.6)
Requires-Dist: nltk (==3.6.2)
Requires-Dist: wordcloud (==1.8.1)
Requires-Dist: matplotlib (==3.3.4)
Requires-Dist: fpdf (==1.7.2)
